archive_reddit_user/__init__.py
archive_reddit_user/authenticator.py
archive_reddit_user/config_manager.py
archive_reddit_user/main.py
archive_reddit_user/rate_limits.py
archive_reddit_user/reddit_archiver.py
archive_reddit_user-0.14.dist-info/METADATA
archive_reddit_user-0.14.dist-info/WHEEL
archive_reddit_user-0.14.dist-info/entry_points.txt
archive_reddit_user-0.14.dist-info/top_level.txt
archive_reddit_user-0.14.dist-info/RECORD
