Metadata-Version: 2.1
Name: archive-reddit-user
Version: 0.14
Summary: A tool to archive Reddit user comments
Home-page: https://github.com/rshin7/archive-reddit-user
Author: Richard Shin
Author-email: webmaster@moogra.com
Project-URL: Bug Reports, https://github.com/rshin7/archive-reddit-user/issues
Project-URL: Source, https://github.com/rshin7/archive-reddit-user/
Keywords: reddit,archiver,comments,backup
Classifier: Development Status :: 4 - Beta
Classifier: Intended Audience :: Developers
Classifier: License :: OSI Approved :: MIT License
Classifier: Programming Language :: Python :: 3
Classifier: Programming Language :: Python :: 3.7
Requires-Dist: praw
Requires-Dist: tqdm
